LICENSE
MANIFEST.in
README.md
setup.cfg
setup.py
rflint/__init__.py
rflint/__main__.py
rflint/common.py
rflint/exceptions.py
rflint/rflint.py
rflint/version.py
rflint/parser/__init__.py
rflint/parser/common.py
rflint/parser/parser.py
rflint/parser/rfkeyword.py
rflint/parser/tables.py
rflint/parser/testcase.py
rflint/parser/util.py
rflint/rules/__init__.py
rflint/rules/duplicates.py
rflint/rules/keywordRules.py
rflint/rules/otherRules.py
rflint/rules/resourceRules.py
rflint/rules/suiteRules.py
rflint/rules/testcaseRules.py
robotframework_lint.egg-info/PKG-INFO
robotframework_lint.egg-info/SOURCES.txt
robotframework_lint.egg-info/dependency_links.txt
robotframework_lint.egg-info/entry_points.txt
robotframework_lint.egg-info/not-zip-safe
robotframework_lint.egg-info/requires.txt
robotframework_lint.egg-info/top_level.txt