Metadata-Version: 1.1
Name: robotframework-lint
Version: 1.1
Summary: Static analysis tool for robotframework plain text files
Home-page: https://github.com/boakley/robotframework-lint/
Author: Bryan Oakley
Author-email: bryan.oakley@gmail.com
License: Apache License 2.0
Keywords: robotframework
Platform: UNKNOWN
Classifier: Development Status :: 5 - Production/Stable
Classifier: License :: OSI Approved :: Apache Software License
Classifier: Operating System :: OS Independent
Classifier: Framework :: Robot Framework
Classifier: Programming Language :: Python
Classifier: Topic :: Software Development :: Testing
Classifier: Topic :: Software Development :: Quality Assurance
Classifier: Intended Audience :: Developers
Classifier: Environment :: Console
